{
	"credit": "Made with Blockbench",
	"texture_size": [64, 64],
	"textures": {
		"0": "tfmg:item/quad_potato_cannon",
		"particle": "tfmg:item/quad_potato_cannon"
	},
	"elements": [
		{
			"name": "Body",
			"from": [5, 1, 2],
			"to": [11, 7, 19],
			"rotation": {"angle": 0, "axis": "y", "origin": [8, 1, 4]},
			"faces": {
				"north": {"uv": [5, 2, 6.5, 3.5], "texture": "#0"},
				"east": {"uv": [0.5, 0, 4.75, 1.5], "texture": "#0"},
				"south": {"uv": [5.5, 5, 7, 6.5], "texture": "#0"},
				"west": {"uv": [0, 1.5, 4.25, 3], "texture": "#0"},
				"up": {"uv": [1.5, 7.75, 0, 3.5], "texture": "#0"},
				"down": {"uv": [3, 3, 1.5, 7.25], "texture": "#0"}
			}
		},
		{
			"name": "Back",
			"from": [8, 3, 19],
			"to": [10, 5, 24],
			"rotation": {"angle": -45, "axis": "z", "origin": [6, 6, 20]},
			"faces": {
				"north": {"uv": [7.75, 6.5, 8.25, 7], "texture": "#0"},
				"east": {"uv": [7.5, 2.25, 8.75, 2.75], "texture": "#0"},
				"south": {"uv": [8, 1.5, 8.5, 2], "texture": "#0"},
				"west": {"uv": [7.5, 2.25, 8.75, 2.75], "texture": "#0"},
				"up": {"uv": [8, 4, 7.5, 2.75], "texture": "#0"},
				"down": {"uv": [8, 2.75, 7.5, 4], "texture": "#0"}
			}
		},
		{
			"name": "Back",
			"from": [10, 5, 19],
			"to": [12, 7, 24],
			"rotation": {"angle": -45, "axis": "z", "origin": [6, 6, 20]},
			"faces": {
				"north": {"uv": [7.75, 6.5, 8.25, 7], "texture": "#0"},
				"east": {"uv": [7.5, 2.25, 8.75, 2.75], "texture": "#0"},
				"south": {"uv": [8, 1.5, 8.5, 2], "texture": "#0"},
				"west": {"uv": [0.5, 7.25, 1.75, 7.75], "texture": "#0"},
				"up": {"uv": [8, 4, 7.5, 2.75], "texture": "#0"},
				"down": {"uv": [8, 2.75, 7.5, 4], "texture": "#0"}
			}
		},
		{
			"name": "Back",
			"from": [8, 7, 19],
			"to": [10, 9, 24],
			"rotation": {"angle": -45, "axis": "z", "origin": [6, 6, 20]},
			"faces": {
				"north": {"uv": [7.75, 6.5, 8.25, 7], "texture": "#0"},
				"east": {"uv": [7.5, 2.25, 8.75, 2.75], "texture": "#0"},
				"south": {"uv": [8, 1.5, 8.5, 2], "texture": "#0"},
				"west": {"uv": [7.5, 2.25, 8.75, 2.75], "texture": "#0"},
				"up": {"uv": [8, 4, 7.5, 2.75], "texture": "#0"},
				"down": {"uv": [2.75, 7.25, 2.25, 8.5], "texture": "#0"}
			}
		},
		{
			"name": "Handle",
			"from": [6, -5, 4],
			"to": [8, 0, 5],
			"rotation": {"angle": -22.5, "axis": "x", "origin": [0, 0, 0]},
			"faces": {
				"north": {"uv": [0, 7.75, 0.5, 9], "texture": "#0"},
				"east": {"uv": [0, 7.75, 0.25, 9], "texture": "#0"},
				"south": {"uv": [0, 7.75, 0.5, 9], "texture": "#0"},
				"west": {"uv": [0.125, 7.75, 0.375, 9], "texture": "#0"},
				"up": {"uv": [7.5, 8.25, 7, 8], "texture": "#0"},
				"down": {"uv": [0.5, 8.875, 0.25, 9], "texture": "#0"}
			}
		},
		{
			"name": "Pipe",
			"from": [11, 3, 5],
			"to": [12, 5, 14],
			"faces": {
				"north": {"uv": [6.875, 0.75, 7.125, 1.25], "texture": "#0"},
				"east": {"uv": [6.75, 0.75, 9, 1.25], "texture": "#0"},
				"south": {"uv": [8, 7.5, 8.25, 8], "texture": "#0"},
				"west": {"uv": [5.5, 6.5, 7.75, 7], "texture": "#0"},
				"up": {"uv": [10.5, 2.5, 10.25, 0.25], "texture": "#0"},
				"down": {"uv": [10.5, 0.25, 10.25, 2.5], "texture": "#0"}
			}
		},
		{
			"name": "Pipe",
			"from": [4, 3, 5],
			"to": [5, 5, 14],
			"faces": {
				"north": {"uv": [7, 1.25, 7.25, 1.75], "texture": "#0"},
				"east": {"uv": [7, 3.5, 9.25, 4], "texture": "#0"},
				"south": {"uv": [8.25, 0.5, 8.5, 1], "texture": "#0"},
				"west": {"uv": [6.75, 1.25, 9, 1.75], "texture": "#0"},
				"up": {"uv": [10.75, 2.5, 10.5, 0.25], "texture": "#0"},
				"down": {"uv": [10.75, 0.25, 10.5, 2.5], "texture": "#0"}
			}
		},
		{
			"name": "Back",
			"from": [6, 5, 19],
			"to": [8, 7, 24],
			"rotation": {"angle": -45, "axis": "z", "origin": [6, 6, 20]},
			"faces": {
				"north": {"uv": [7.75, 6.5, 8.25, 7], "texture": "#0"},
				"east": {"uv": [7.25, 0, 8.5, 0.5], "texture": "#0"},
				"south": {"uv": [8, 1.5, 8.5, 2], "texture": "#0"},
				"west": {"uv": [7.5, 2.25, 8.75, 2.75], "texture": "#0"},
				"up": {"uv": [8, 4, 7.5, 2.75], "texture": "#0"},
				"down": {"uv": [8, 2.75, 7.5, 4], "texture": "#0"}
			}
		},
		{
			"name": "Tank",
			"from": [6, 7, 11],
			"to": [10, 9, 17],
			"faces": {
				"north": {"uv": [7.75, 6.75, 8.75, 7.25], "texture": "#0"},
				"east": {"uv": [5.5, 7.25, 7, 7.75], "texture": "#0"},
				"south": {"uv": [7.75, 6.75, 8.75, 7.25], "texture": "#0"},
				"west": {"uv": [5.5, 7.25, 7, 7.75], "texture": "#0"},
				"up": {"uv": [4, 8, 3, 6.5], "texture": "#0"},
				"down": {"uv": [7.5, 1.5, 6.5, 3], "texture": "#0"}
			}
		},
		{
			"name": "Pipe",
			"from": [5, 7, 14],
			"to": [7, 8, 16],
			"faces": {
				"north": {"uv": [7, 4.25, 7.5, 4.5], "texture": "#0"},
				"east": {"uv": [8.25, 1.25, 8.75, 1.5], "texture": "#0"},
				"south": {"uv": [7, 4.5, 7.5, 4.75], "texture": "#0"},
				"west": {"uv": [8.25, 6.75, 8.75, 7], "texture": "#0"},
				"up": {"uv": [7.5, 5.5, 7, 5], "texture": "#0"},
				"down": {"uv": [8.5, 2.5, 8, 3], "texture": "#0"}
			}
		},
		{
			"name": "Pipe",
			"from": [9, 7, 14],
			"to": [11, 8, 16],
			"faces": {
				"north": {"uv": [7, 4.5, 7.5, 4.75], "texture": "#0"},
				"east": {"uv": [7.5, 8.25, 8, 8.5], "texture": "#0"},
				"south": {"uv": [7, 4.5, 7.5, 4.75], "texture": "#0"},
				"west": {"uv": [8.25, 7.75, 8.75, 8], "texture": "#0"},
				"up": {"uv": [7.5, 5.5, 7, 5], "texture": "#0"},
				"down": {"uv": [6.5, 8, 6, 8.5], "texture": "#0"}
			}
		},
		{
			"name": "Pipe",
			"from": [11, 3, 14],
			"to": [12, 8, 16],
			"faces": {
				"north": {"uv": [7, 4.25, 7.25, 5.5], "texture": "#0"},
				"east": {"uv": [7, 4.25, 7.5, 5.5], "texture": "#0"},
				"south": {"uv": [7.25, 4.25, 7.5, 5.5], "texture": "#0"},
				"west": {"uv": [0.5, 7.75, 1, 8.75], "texture": "#0"},
				"up": {"uv": [7.25, 5.5, 7, 5], "texture": "#0"},
				"down": {"uv": [7.5, 5, 7.25, 5.5], "texture": "#0"}
			}
		},
		{
			"name": "Pipe",
			"from": [4, 3, 14],
			"to": [5, 8, 16],
			"faces": {
				"north": {"uv": [7.25, 4.25, 7.5, 5.5], "texture": "#0"},
				"east": {"uv": [7.75, 0.5, 8.25, 1.5], "texture": "#0"},
				"south": {"uv": [7, 4.25, 7.25, 5.5], "texture": "#0"},
				"west": {"uv": [7, 4.25, 7.5, 5.5], "texture": "#0"},
				"up": {"uv": [7.5, 5.5, 7.25, 5], "texture": "#0"},
				"down": {"uv": [7.25, 5, 7, 5.5], "texture": "#0"}
			}
		},
		{
			"name": "Grip",
			"from": [7, 0, 2],
			"to": [9, 1, 19],
			"faces": {
				"north": {"uv": [8.5, 0.5, 9, 0.75], "texture": "#0"},
				"east": {"uv": [5.5, 6.5, 10, 6.75], "texture": "#0"},
				"south": {"uv": [6, 6.25, 6.5, 6.5], "texture": "#0"},
				"west": {"uv": [5.5, 6.5, 10, 6.75], "texture": "#0"},
				"up": {"uv": [5.5, 8, 5, 3.5], "texture": "#0"},
				"down": {"uv": [5, 5, 4.5, 9.5], "texture": "#0"}
			}
		},
		{
			"name": "Back",
			"from": [5, 1, 24],
			"to": [11, 7, 25],
			"rotation": {"angle": 0, "axis": "y", "origin": [0, 0, -1]},
			"faces": {
				"north": {"uv": [5.5, 3.5, 7, 5], "texture": "#0"},
				"east": {"uv": [1.5, 7.75, 1.75, 9.25], "texture": "#0"},
				"south": {"uv": [5.5, 3.5, 7, 5], "texture": "#0"},
				"west": {"uv": [1.125, 8.125, 1.375, 9.625], "texture": "#0"},
				"up": {"uv": [1.625, 9.375, 0.125, 9.125], "texture": "#0"},
				"down": {"uv": [1.5, 9.5, 0, 9.75], "texture": "#0"}
			}
		},
		{
			"from": [4, 0, 0],
			"to": [12, 8, 2],
			"faces": {
				"north": {"uv": [3, 3, 5, 5], "texture": "#0"},
				"east": {"uv": [2, 10, 2.5, 12], "texture": "#0"},
				"south": {"uv": [3, 3, 5, 5], "texture": "#0"},
				"west": {"uv": [2, 10, 2.5, 12], "texture": "#0"},
				"up": {"uv": [2, 11.125, 0, 10.625], "texture": "#0"},
				"down": {"uv": [2, 10.625, 0, 11.125], "texture": "#0"}
			}
		}
	],
	"display": {
		"thirdperson_righthand": {
			"translation": [1.75, 6.75, 3.75]
		},
		"thirdperson_lefthand": {
			"translation": [1.75, 6.75, 3.75]
		},
		"firstperson_righthand": {
			"translation": [0, 10.75, 5.25]
		},
		"firstperson_lefthand": {
			"translation": [0, 10.75, 5.25]
		},
		"ground": {
			"rotation": [0, 0, 90],
			"translation": [-3.5, 0.75, -4.25]
		},
		"gui": {
			"rotation": [40, 39, -6],
			"translation": [-1.5, 3.5, 0],
			"scale": [0.7, 0.7, 0.7]
		},
		"head": {
			"translation": [0, 14, -2.75]
		},
		"fixed": {
			"rotation": [-90, 180, 0],
			"translation": [0, 4.25, -4.5],
			"scale": [0.8, 0.8, 0.8]
		}
	},
	"groups": [
		{
			"name": "group",
			"origin": [0, 0, 0],
			"color": 0,
			"children": [0, 1, 2, 3, 4, 5, 6, 7, 8, 9, 10, 11, 12, 13, 14, 15]
		}
	]
}